pseudo_python/__init__.py
pseudo_python/api_translator.py
pseudo_python/ast_translator.py
pseudo_python/builtin_typed_api.py
pseudo_python/env.py
pseudo_python/errors.py
pseudo_python/helpers.py
pseudo_python/main.py
pseudo_python/parser.py
pseudo_python/standard.py
pseudo_python-0.2.32.dist-info/DESCRIPTION.rst
pseudo_python-0.2.32.dist-info/METADATA
pseudo_python-0.2.32.dist-info/RECORD
pseudo_python-0.2.32.dist-info/WHEEL
pseudo_python-0.2.32.dist-info/entry_points.txt
pseudo_python-0.2.32.dist-info/metadata.json
pseudo_python-0.2.32.dist-info/top_level.txt
