Metadata-Version: 2.0
Name: pseudo-python
Version: 0.2.32
Summary: a python3 to pseudo compiler
Home-page: https://github.com/alehander42/pseudo-python
Author: Alexander Ivanov
Author-email: alehander42@gmail.com
License: MIT
Download-URL: https://github.com/alehander42/pseudo-python/archive/v0.2.tar.gz
Keywords: compiler,generation,c++,ruby,c#,javascript,go,python,pseudo
Platform: UNKNOWN
Classifier: Development Status :: 4 - Beta
Classifier: Programming Language :: Python
Classifier: Programming Language :: JavaScript
Classifier: Programming Language :: Python :: 3
Classifier: Programming Language :: Python :: 3.2
Classifier: Programming Language :: Python :: 3.3
Classifier: Programming Language :: Python :: 3.4
Classifier: Intended Audience :: Developers
Classifier: License :: OSI Approved :: MIT License
Requires-Dist: PyYAML
Requires-Dist: colorama
Requires-Dist: termcolor
Requires-Dist: pseudo (>=0.2.3)
